Metadata-Version: 1.0
Name: markdown2jupyter
Version: 1.0
Summary: Markdown to Jupyter notebook converter
Home-page: UNKNOWN
Author: Jan Papousek
Author-email: jan.papousek@gmail.com
License: UNKNOWN
Platform: UNKNOWN
